setup.py
glamkit_performance.egg-info/PKG-INFO
glamkit_performance.egg-info/SOURCES.txt
glamkit_performance.egg-info/dependency_links.txt
glamkit_performance.egg-info/not-zip-safe
glamkit_performance.egg-info/top_level.txt
mediahash/__init__.py
mediahash/models.py
mediahash/templatetags/__init__.py
mediahash/templatetags/mediahash.py