Metadata-Version: 1.0
Name: glamkit-performance
Version: 0.5.3
Summary: A template tag to help with concurrent media serving from Django
Home-page: http://glamkit.org/
Author: Thomas Ashelford
Author-email: thomas@interaction.net.au
License: UNKNOWN
Platform: UNKNOWN
Classifier: Development Status :: 4 - Beta
Classifier: Environment :: Web Environment
Classifier: Intended Audience :: Developers
Classifier: License :: OSI Approved :: BSD License
Classifier: Operating System :: OS Independent
Classifier: Programming Language :: Python
Classifier: Framework :: Django
